cartesian_tree-0.3.0.dist-info/METADATA
cartesian_tree-0.3.0.dist-info/WHEEL
cartesian_tree-0.3.0.dist-info/licenses/license-mit
cartesian_tree/__init__.py
cartesian_tree/_cartesian_tree.cp314-win_amd64.pyd
cartesian_tree/angles.py
cartesian_tree/base_types.py
cartesian_tree/lazy_access.py
cartesian_tree/lib.py
cartesian_tree/py.typed
cartesian_tree/quaternion.py
cartesian_tree-0.3.0.dist-info/RECORD
