Metadata-Version: 2.4
Name: cartesian-tree
Version: 0.3.0
Classifier: Programming Language :: Python
Requires-Dist: cartesian-tree[lint] ; extra == 'dev'
Requires-Dist: cartesian-tree[test] ; extra == 'dev'
Requires-Dist: cartesian-tree[build] ; extra == 'dev'
Requires-Dist: ruff==0.12.4 ; extra == 'lint'
Requires-Dist: mypy==1.17.0 ; extra == 'lint'
Requires-Dist: pytest==8.4.1 ; extra == 'test'
Requires-Dist: maturin==1.8.6 ; extra == 'build'
Provides-Extra: dev
Provides-Extra: lint
Provides-Extra: test
Provides-Extra: build
License-File: license-mit
Summary: Build hierarchical Cartesian coordinate systems to easily transform poses.
Keywords: Cartesian,coordinate systems,transform,poses
Home-Page: https://github.com/Kn0g/cartesian-tree
Author: Kn0g
Maintainer: Kn0g
Requires-Python: >=3.9
